shinobi/__init__.py
shinobi/cli.py
shinobi/commands/__init__.py
shinobi/commands/init.py
shinobi/config/__init__.py
shinobi/config/project_config.py
shinobi/core/__init__.py
shinobi/core/utils.py
shinobi/templates/__init__.py
shinobi/templates/gitignore.template
shinobi/templates/ci/github_workflows/lint.yml
shinobi/templates/ci/github_workflows/test.yml
shinobi/templates/docs/README.md.template
shinobi/templates/ide/cursor/rules/use-uv-always.mdc
shinobi/templates/ide/vscode/extensions.json
shinobi/templates/ide/vscode/settings.json
shinobi/templates/license/mit.template
shinobi/templates/project/pre-commit-config.yaml
shinobi/templates/project/pyproject.toml.template
shinobi/validation/__init__.py
shinobi/validation/validators.py
shinobi-0.1.2.dist-info/METADATA
shinobi-0.1.2.dist-info/WHEEL
shinobi-0.1.2.dist-info/entry_points.txt
shinobi-0.1.2.dist-info/licenses/LICENSE
shinobi-0.1.2.dist-info/RECORD
