Metadata-Version: 2.4
Name: shinobi
Version: 0.1.2
Summary: Enhanced project initialization tool built on top of uv
Author: Ian Timmis
License: MIT
License-File: LICENSE
Requires-Python: >=3.8
Requires-Dist: jinja2>=3.1.3
Requires-Dist: questionary>=2.0.1
Requires-Dist: rich>=13.7.0
Requires-Dist: typer>=0.9.0
